util/__init__.py
util/tools.py
GFP_TEST-0.1.0.dist-info/METADATA
GFP_TEST-0.1.0.dist-info/WHEEL
GFP_TEST-0.1.0.dist-info/top_level.txt
GFP_TEST-0.1.0.dist-info/RECORD
