Metadata-Version: 2.1
Name: GFP-TEST
Version: 0.1.0
Summary: UNKNOWN
Home-page: https://github.com/Miss-chan/pypi_package_test
Author: UNKNOWN
Author-email: UNKNOWN
License: UNKNOWN
Platform: UNKNOWN
Requires-Dist: scrapy (>=1.5.1)
